pymorant/__init__.py
pymorant/chatbot.py
pymorant/chatbot_quadrant.py
pymorant/chatea_conmigo.py
pymorant/costosMorant.py
pymorant/llm.py
pymorant/utils.py
pymorant-2.0.2.dist-info/LICENSE
pymorant-2.0.2.dist-info/METADATA
pymorant-2.0.2.dist-info/WHEEL
pymorant-2.0.2.dist-info/top_level.txt
pymorant-2.0.2.dist-info/RECORD
