Metadata-Version: 2.1
Name: pymorant
Version: 2.0.2
Summary: Paquetería de funciones para el equipo de AI Morant en Python
Home-page: https://github.com/morant-consultores/py_morant
Author: Equipo AI Morant
Author-email: abravo@morant.com.mx
Project-URL: Bug Tracker, https://github.com/morant-consultores/py_morant/issues
Classifier: Programming Language :: Python :: 3
Classifier: License :: OSI Approved :: MIT License
Classifier: Operating System :: OS Independent
Requires-Python: >=3.6
License-File: LICENSE
Requires-Dist: pyodbc ==4.0.34
Requires-Dist: pytz ==2024.1
Requires-Dist: SQLAlchemy ==2.0.25
Requires-Dist: typing-extensions ==4.9.0
